<?xml version="1.0" encoding="UTF-8"?><?xml-stylesheet type='text/xsl' href='_UpgradeReport_Files/UpgradeReport.xslt'?><UpgradeLog>
<Properties><Property Name="Solution" Value="WindowsAzurePlatformBook2E">
</Property><Property Name="Solution File" Value="C:\Tejaswi\Publications\Windows Azure Patterns\Code\WindowsAzurePlatformBook2E\WindowsAzurePlatformBook2E.sln">
</Property><Property Name="Date" Value="Saturday, November 26, 2011">
</Property><Property Name="Time" Value="0:12 AM">
</Property></Properties><Event ErrorLevel="0" Project="C:\Tejaswi\Publications\Windows Azure Patterns\Code\WindowsAzurePlatformBook2E\Ch2Solution\HelloAzureCloud\HelloAzureCloud.ccproj" Source="Ch2Solution\HelloAzureCloud\HelloAzureCloud.ccproj" Description="The file is read-only, attempting to check-out if under source control">
</Event><Event ErrorLevel="0" Project="C:\Tejaswi\Publications\Windows Azure Patterns\Code\WindowsAzurePlatformBook2E\Ch2Solution\HelloAzureCloud\HelloAzureCloud.ccproj" Source="Ch2Solution\HelloAzureCloud\HelloAzureCloud.ccproj" Description="The file successfully checked out.">
</Event><Event ErrorLevel="0" Project="C:\Tejaswi\Publications\Windows Azure Patterns\Code\WindowsAzurePlatformBook2E\Ch2Solution\HelloAzureCloud\HelloAzureCloud.ccproj" Source="Ch2Solution\HelloAzureCloud\HelloAzureCloud.ccproj" Description="Upgraded ProductVersion value to 1.6.">
</Event><Event ErrorLevel="3" Project="C:\Tejaswi\Publications\Windows Azure Patterns\Code\WindowsAzurePlatformBook2E\Ch2Solution\HelloAzureCloud\HelloAzureCloud.ccproj" Source="Ch2Solution\HelloAzureCloud\HelloAzureCloud.ccproj" Description="Converted">
</Event><Event ErrorLevel="0" Project="C:\Tejaswi\Publications\Windows Azure Patterns\Code\WindowsAzurePlatformBook2E\Ch2Solution\HelloAzureCloud\HelloAzureCloud.ccproj" Source="Ch2Solution\HelloAzureCloud\HelloAzureCloud.ccproj" Description="Upgrade CloudExtensionsDir value to $(MSBuildExtensionsPath)\Microsoft\VisualStudio\v$(VisualStudioVersion)\Windows Azure Tools\1.6\.">
</Event><Event ErrorLevel="0" Project="C:\Tejaswi\Publications\Windows Azure Patterns\Code\WindowsAzurePlatformBook2E\Ch2Solution\HelloAzureCloud\HelloAzureCloud.ccproj" Source="Ch2Solution\HelloAzureCloud\HelloAzureCloud.ccproj" Description="Generate a default Publish Profile Profiles\silverliningProduction.azurePubxml based on previous user's setting and add it to the project.">
</Event><Event ErrorLevel="0" Project="HelloWebRole" Source="Ch2Solution\HelloWebRole\HelloWebRole.csproj" Description="The project file does not require conversion.">
</Event><Event ErrorLevel="3" Project="HelloWebRole" Source="Ch2Solution\HelloWebRole\HelloWebRole.csproj" Description="No Conversion Required">
</Event><Event ErrorLevel="0" Project="HelloWorkerRole" Source="Ch2Solution\HelloWorkerRole\HelloWorkerRole.csproj" Description="The project file does not require conversion.">
</Event><Event ErrorLevel="3" Project="HelloWorkerRole" Source="Ch2Solution\HelloWorkerRole\HelloWorkerRole.csproj" Description="No Conversion Required">
</Event><Event ErrorLevel="0" Project="csmanage" Source="Ch2Solution\WindowsAzureServiceManagement\csmanage\csmanage\csmanage.csproj" Description="The project file does not require conversion.">
</Event><Event ErrorLevel="3" Project="csmanage" Source="Ch2Solution\WindowsAzureServiceManagement\csmanage\csmanage\csmanage.csproj" Description="No Conversion Required">
</Event><Event ErrorLevel="0" Project="Microsoft.Samples.WindowsAzure.ServiceManagement" Source="Ch2Solution\WindowsAzureServiceManagement\Microsoft.Samples.WindowsAzure.ServiceManagement\Microsoft.Samples.WindowsAzure.ServiceManagement.csproj" Description="The project file does not require conversion.">
</Event><Event ErrorLevel="3" Project="Microsoft.Samples.WindowsAzure.ServiceManagement" Source="Ch2Solution\WindowsAzureServiceManagement\Microsoft.Samples.WindowsAzure.ServiceManagement\Microsoft.Samples.WindowsAzure.ServiceManagement.csproj" Description="No Conversion Required">
</Event><Event ErrorLevel="0" Project="ServiceManagement" Source="Ch2Solution\WindowsAzureServiceManagement\ServiceManagement\ServiceManagement\ServiceManagement.csproj" Description="The project file does not require conversion.">
</Event><Event ErrorLevel="3" Project="ServiceManagement" Source="Ch2Solution\WindowsAzureServiceManagement\ServiceManagement\ServiceManagement\ServiceManagement.csproj" Description="No Conversion Required">
</Event><Event ErrorLevel="0" Project="ProAzureCommonLib" Source="ProAzureCommon\ProAzureCommonLib\ProAzureCommonLib.csproj" Description="The project file does not require conversion.">
</Event><Event ErrorLevel="3" Project="ProAzureCommonLib" Source="ProAzureCommon\ProAzureCommonLib\ProAzureCommonLib.csproj" Description="No Conversion Required">
</Event><Event ErrorLevel="0" Project="C:\Tejaswi\Publications\Windows Azure Patterns\Code\WindowsAzurePlatformBook2E\Ch2Solution\WebWorkerComm\WebWorkerComm.ccproj" Source="Ch2Solution\WebWorkerComm\WebWorkerComm.ccproj" Description="The file is read-only, attempting to check-out if under source control">
</Event><Event ErrorLevel="0" Project="C:\Tejaswi\Publications\Windows Azure Patterns\Code\WindowsAzurePlatformBook2E\Ch2Solution\WebWorkerComm\WebWorkerComm.ccproj" Source="Ch2Solution\WebWorkerComm\WebWorkerComm.ccproj" Description="The file successfully checked out.">
</Event><Event ErrorLevel="0" Project="C:\Tejaswi\Publications\Windows Azure Patterns\Code\WindowsAzurePlatformBook2E\Ch2Solution\WebWorkerComm\WebWorkerComm.ccproj" Source="Ch2Solution\WebWorkerComm\WebWorkerComm.ccproj" Description="Upgraded ProductVersion value to 1.6.">
</Event><Event ErrorLevel="3" Project="C:\Tejaswi\Publications\Windows Azure Patterns\Code\WindowsAzurePlatformBook2E\Ch2Solution\WebWorkerComm\WebWorkerComm.ccproj" Source="Ch2Solution\WebWorkerComm\WebWorkerComm.ccproj" Description="Converted">
</Event><Event ErrorLevel="0" Project="C:\Tejaswi\Publications\Windows Azure Patterns\Code\WindowsAzurePlatformBook2E\Ch2Solution\WebWorkerComm\WebWorkerComm.ccproj" Source="Ch2Solution\WebWorkerComm\WebWorkerComm.ccproj" Description="Upgrade CloudExtensionsDir value to $(MSBuildExtensionsPath)\Microsoft\VisualStudio\v$(VisualStudioVersion)\Windows Azure Tools\1.6\.">
</Event><Event ErrorLevel="0" Project="ProAzureCommon" Source="Ch2Solution\ProAzureCommon\ProAzureCommon.csproj" Description="The project file does not require conversion.">
</Event><Event ErrorLevel="3" Project="ProAzureCommon" Source="Ch2Solution\ProAzureCommon\ProAzureCommon.csproj" Description="No Conversion Required">
</Event><Event ErrorLevel="0" Project="WebWorkerExch_WebRole" Source="Ch2Solution\WebWorkerExch_WebRole\WebWorkerExch_WebRole.csproj" Description="The project file does not require conversion.">
</Event><Event ErrorLevel="3" Project="WebWorkerExch_WebRole" Source="Ch2Solution\WebWorkerExch_WebRole\WebWorkerExch_WebRole.csproj" Description="No Conversion Required">
</Event><Event ErrorLevel="0" Project="WebWorkerExch_WorkerRole" Source="Ch2Solution\WebWorkerExch_WorkerRole\WebWorkerExch_WorkerRole.csproj" Description="The project file does not require conversion.">
</Event><Event ErrorLevel="3" Project="WebWorkerExch_WorkerRole" Source="Ch2Solution\WebWorkerExch_WorkerRole\WebWorkerExch_WorkerRole.csproj" Description="No Conversion Required">
</Event><Event ErrorLevel="0" Project="CDNTest" Source="Ch3and4Solution\CDNTest\CDNTest.csproj" Description="The project file does not require conversion.">
</Event><Event ErrorLevel="3" Project="CDNTest" Source="Ch3and4Solution\CDNTest\CDNTest.csproj" Description="No Conversion Required">
</Event><Event ErrorLevel="0" Project="Drives" Source="Ch3and4Solution\Drives\Drives.csproj" Description="The project file does not require conversion.">
</Event><Event ErrorLevel="3" Project="Drives" Source="Ch3and4Solution\Drives\Drives.csproj" Description="No Conversion Required">
</Event><Event ErrorLevel="0" Project="C:\Tejaswi\Publications\Windows Azure Patterns\Code\WindowsAzurePlatformBook2E\Ch3and4Solution\DrivesExample\DrivesExample.ccproj" Source="Ch3and4Solution\DrivesExample\DrivesExample.ccproj" Description="The file is read-only, attempting to check-out if under source control">
</Event><Event ErrorLevel="0" Project="C:\Tejaswi\Publications\Windows Azure Patterns\Code\WindowsAzurePlatformBook2E\Ch3and4Solution\DrivesExample\DrivesExample.ccproj" Source="Ch3and4Solution\DrivesExample\DrivesExample.ccproj" Description="The file successfully checked out.">
</Event><Event ErrorLevel="0" Project="C:\Tejaswi\Publications\Windows Azure Patterns\Code\WindowsAzurePlatformBook2E\Ch3and4Solution\DrivesExample\DrivesExample.ccproj" Source="Ch3and4Solution\DrivesExample\DrivesExample.ccproj" Description="Upgraded ProductVersion value to 1.6.">
</Event><Event ErrorLevel="3" Project="C:\Tejaswi\Publications\Windows Azure Patterns\Code\WindowsAzurePlatformBook2E\Ch3and4Solution\DrivesExample\DrivesExample.ccproj" Source="Ch3and4Solution\DrivesExample\DrivesExample.ccproj" Description="Converted">
</Event><Event ErrorLevel="0" Project="C:\Tejaswi\Publications\Windows Azure Patterns\Code\WindowsAzurePlatformBook2E\Ch3and4Solution\DrivesExample\DrivesExample.ccproj" Source="Ch3and4Solution\DrivesExample\DrivesExample.ccproj" Description="Upgrade CloudExtensionsDir value to $(MSBuildExtensionsPath)\Microsoft\VisualStudio\v$(VisualStudioVersion)\Windows Azure Tools\1.6\.">
</Event><Event ErrorLevel="0" Project="vhddownload" Source="Ch3and4Solution\vhddownload\vhddownload.csproj" Description="The project file does not require conversion.">
</Event><Event ErrorLevel="3" Project="vhddownload" Source="Ch3and4Solution\vhddownload\vhddownload.csproj" Description="No Conversion Required">
</Event><Event ErrorLevel="0" Project="vhdupload" Source="Ch3and4Solution\vhdupload\vhdupload.csproj" Description="The project file does not require conversion.">
</Event><Event ErrorLevel="3" Project="vhdupload" Source="Ch3and4Solution\vhdupload\vhdupload.csproj" Description="No Conversion Required">
</Event><Event ErrorLevel="0" Project="Windows Azure Storage Operations" Source="Ch3and4Solution\Windows Azure Storage\Windows Azure Storage Operations.csproj" Description="The project file does not require conversion.">
</Event><Event ErrorLevel="3" Project="Windows Azure Storage Operations" Source="Ch3and4Solution\Windows Azure Storage\Windows Azure Storage Operations.csproj" Description="No Conversion Required">
</Event><Event ErrorLevel="0" Project="ProAzureReaderTracker_WebRole" Source="Ch5Solution\ProAzureReaderTracker_WebRole\ProAzureReaderTracker_WebRole.csproj" Description="The project file does not require conversion.">
</Event><Event ErrorLevel="3" Project="ProAzureReaderTracker_WebRole" Source="Ch5Solution\ProAzureReaderTracker_WebRole\ProAzureReaderTracker_WebRole.csproj" Description="No Conversion Required">
</Event><Event ErrorLevel="0" Project="ProAzureTableStorageClasses" Source="Ch5Solution\ProAzureTableStorageClasses\ProAzureTableStorageClasses.csproj" Description="The project file does not require conversion.">
</Event><Event ErrorLevel="3" Project="ProAzureTableStorageClasses" Source="Ch5Solution\ProAzureTableStorageClasses\ProAzureTableStorageClasses.csproj" Description="No Conversion Required">
</Event><Event ErrorLevel="0" Project="C:\Tejaswi\Publications\Windows Azure Patterns\Code\WindowsAzurePlatformBook2E\Ch5Solution\ProAzureReaderTracker\ProAzureReaderTracker.ccproj" Source="Ch5Solution\ProAzureReaderTracker\ProAzureReaderTracker.ccproj" Description="The file is read-only, attempting to check-out if under source control">
</Event><Event ErrorLevel="0" Project="C:\Tejaswi\Publications\Windows Azure Patterns\Code\WindowsAzurePlatformBook2E\Ch5Solution\ProAzureReaderTracker\ProAzureReaderTracker.ccproj" Source="Ch5Solution\ProAzureReaderTracker\ProAzureReaderTracker.ccproj" Description="The file successfully checked out.">
</Event><Event ErrorLevel="0" Project="C:\Tejaswi\Publications\Windows Azure Patterns\Code\WindowsAzurePlatformBook2E\Ch5Solution\ProAzureReaderTracker\ProAzureReaderTracker.ccproj" Source="Ch5Solution\ProAzureReaderTracker\ProAzureReaderTracker.ccproj" Description="Upgraded ProductVersion value to 1.6.">
</Event><Event ErrorLevel="3" Project="C:\Tejaswi\Publications\Windows Azure Patterns\Code\WindowsAzurePlatformBook2E\Ch5Solution\ProAzureReaderTracker\ProAzureReaderTracker.ccproj" Source="Ch5Solution\ProAzureReaderTracker\ProAzureReaderTracker.ccproj" Description="Converted">
</Event><Event ErrorLevel="0" Project="C:\Tejaswi\Publications\Windows Azure Patterns\Code\WindowsAzurePlatformBook2E\Ch5Solution\ProAzureReaderTracker\ProAzureReaderTracker.ccproj" Source="Ch5Solution\ProAzureReaderTracker\ProAzureReaderTracker.ccproj" Description="Upgrade CloudExtensionsDir value to $(MSBuildExtensionsPath)\Microsoft\VisualStudio\v$(VisualStudioVersion)\Windows Azure Tools\1.6\.">
</Event><Event ErrorLevel="0" Project="" Source="WindowsAzurePlatformBook2E.sln" Description="The solution file does not require conversion.">
</Event><Event ErrorLevel="3" Project="" Source="WindowsAzurePlatformBook2E.sln" Description="No Conversion Required">
</Event></UpgradeLog>